phraseg/__init__.py
phraseg/main.py
phraseg-1.2.7.dist-info/LICENSE
phraseg-1.2.7.dist-info/METADATA
phraseg-1.2.7.dist-info/WHEEL
phraseg-1.2.7.dist-info/top_level.txt
phraseg-1.2.7.dist-info/RECORD
