Metadata-Version: 2.1
Name: phraseg
Version: 1.2.7
Summary: unsupervised phrase discover - 無監督新詞發現
Home-page: https://github.com/voidful/phraseg
Author: voidful
Author-email: voidful.stack@gmail.com
License: UNKNOWN
Keywords: phrase nlp word segment 斷詞 分詞 新詞發現 新詞
Platform: UNKNOWN
Classifier: Development Status :: 4 - Beta
Classifier: Intended Audience :: Developers
Classifier: Topic :: Software Development :: Build Tools
Classifier: License :: OSI Approved :: MIT License
Classifier: Programming Language :: Python :: 3
Classifier: Programming Language :: Python :: 3.4
Classifier: Programming Language :: Python :: 3.5
Classifier: Programming Language :: Python :: 3.6
License-File: LICENSE
Requires-Dist: nlp2 (>=1.6.1)
Requires-Dist: tqdm
